bdtime/__init__.py
bdtime/datetime_utils.py
bdtime/get_cpu_info.py
bdtime/my_log.py
bdtime/my_time.py
bdtime/utils.py
bdtime/with_timer.py
bdtime-1.0.6.dist-info/DESCRIPTION.rst
bdtime-1.0.6.dist-info/METADATA
bdtime-1.0.6.dist-info/RECORD
bdtime-1.0.6.dist-info/WHEEL
bdtime-1.0.6.dist-info/metadata.json
bdtime-1.0.6.dist-info/top_level.txt
