Metadata-Version: 2.0
Name: bdtime
Version: 1.0.6
Summary: bode's private time model.
Home-page: https://github.com/bode135/bdtime
Author: bode135
Author-email: 2248270222@qq.com
License: UNKNOWN
Platform: UNKNOWN
Classifier: Programming Language :: Python :: 3
Classifier: License :: OSI Approved :: MIT License
Classifier: Operating System :: OS Independent
